[{"loc1":"牧野区","loc2":["北环外","大学城","定国湖","二十七中","二中","凤泉区","高铁东站","河师大","黄岗","环宇","理想城","牧野公园","牛村","胜利北街","水产大世界","万达","卫辉市","伟业","新乡县","新乡站","西外环","西王村"]},{"loc1":"红旗区","loc2":["宝龙","大学城","东南外环","二中","橄榄城","高铁东站","光彩","洪门","花卉市场","柳青路","理想城","牧野公园","南环外","汽车东站","人民公园","市政府","卫辉市","伟业","新乡县","新乡站","新悦城","延津县"]},{"loc1":"卫滨区","loc2":["八里营","北环外","二十七中","二中","光彩","恒大","柳青路","绿地","南环外","人民公园","市中心医院","新建街","新乡县","新乡站","新悦城","西外环","植物园"]},{"loc1":"凤泉区","loc2":["北环外","凤泉区","卫辉市","新乡县"]},{"loc1":"卫辉市","loc2":["北环外","凤泉区","高铁东站","卫辉市","延津县"]},{"loc1":"辉县市","loc2":["凤泉区","辉县市","卫辉市"]},{"loc1":"新乡县","loc2":["北环外","东南外环","凤泉区","南环外","新乡县","西外环","延津县","原阳县"]},{"loc1":"原阳县","loc2":["封丘县","获嘉县","平原新区","新乡县","延津县","原阳县"]},{"loc1":"封丘县","loc2":["长垣县","封丘县","延津县","原阳县"]},{"loc1":"延津县","loc2":["东南外环","封丘县","高铁东站","卫辉市","新乡县","延津县","原阳县"]},{"loc1":"获嘉县","loc2":["获嘉县","新乡县","原阳县"]},{"loc1":"长垣县","loc2":["长垣县","封丘县"]}]