[{"loc1":"4号线","loc2":["杜家坪站","长沙火车南站（磁悬浮高铁站）站","平阳站","光达站","粟塘站","沙湾公园站","圭塘站","树木岭站","赤岗岭站","砂子塘站","黄土岭站","碧沙湖站","阜埠河站","湖南大学站","湖南师大站","溁湾镇站","望月湖站","六沟垅站","观沙岭站","茶子山站","福元大桥西站","汉王陵公园站","湘江新城站","月亮岛西站","罐子岭站"]},{"loc1":"磁浮快线","loc2":["长沙火车南站（磁悬浮高铁站）站","磁浮高铁站站","磁浮榔梨站","磁浮机场站站"]},{"loc1":"5号线","loc2":["水渡河站","土桥站","白茅铺站","月湖公园北站","马栏山站","鸭子铺站","火炬村站","马王堆站","万家丽广场站","芙蓉区政府站","高桥南站","高桥北站","圭塘站","木桥站","雨花区政府站","大塘站","板塘冲站","毛竹塘站"]},{"loc1":"3号线","loc2":["山塘站","洋湖湿地站","洋湖新城站","阳光站","中南大学站","阜埠河站","灵官渡站","侯家塘站","东塘站","桂花公园站","阿弥岭站","朝阳村站","长沙火车站站","烈士公园东站","丝茅冲站","四方坪站","雅鹊湖站","长沙大学站","月湖公园北站","湘龙站","星沙站","松雅湖(南)站","星沙文化中心站","螺丝塘站","广生站"]},{"loc1":"1号线","loc2":["尚双塘站","中信广场站","大托站","桂花坪站","省政府站","友谊路站","铁道学院站","涂家冲站","黄土岭站","南湖路站","侯家塘站","南门口站","黄兴广场站","五一广场站","培元桥站","文昌阁站","省政府·清风站","开福寺站","北辰三角洲站","马厂站","开福区政府站"]},{"loc1":"2号线","loc2":["光达站","长沙火车南站（磁悬浮高铁站）站","杜花路站","沙湾公园站","长沙大道站","人民东路站","万家丽广场站","锦泰广场站","长沙火车站站","袁家岭站","迎宾路口站","芙蓉广场站","五一广场站","湘江中路站","橘子洲站","橘子洲·青莲站","溁湾镇站","西湖公园站","金星路站","望城坡站","梅溪湖东站","文化艺术中心站","麓云路站","梅溪湖西站"]}]